{
  "version": 1,
  "updated_utc": "2026-02-17T23:40:55Z",
  "books": [
    {
      "id": "Afganistan-a2-es",
      "title": "Afganistan — Perfil del país (A2)",
      "language": "es",
      "level": "A2",
      "genre": [
        "Non-fiction"
      ],
      "difficulty": 2,
      "enjoyment": 3,
      "path": "books/es/a2/Afganistan-a2-es.json",
      "word_count": 1450
    },
    {
      "id": "Argentina-a2-es",
      "title": "Argentina — Perfil del país (A2)",
      "language": "es",
      "level": "A2",
      "genre": [
        "Non-fiction"
      ],
      "difficulty": 2,
      "enjoyment": 3,
      "path": "books/es/a2/Argentina-a2-es.json",
      "word_count": 1822
    },
    {
      "id": "Belgium-a2-es",
      "title": "Belgium — Perfil del país (A2)",
      "language": "es",
      "level": "A2",
      "genre": [
        "Non-fiction"
      ],
      "difficulty": 2,
      "enjoyment": 3,
      "path": "books/es/a2/Belgium-a2-es.json",
      "word_count": 1682
    },
    {
      "id": "Benin-a2-es",
      "title": "Benin — Perfil del país (A2)",
      "language": "es",
      "level": "A2",
      "genre": [
        "Non-fiction"
      ],
      "difficulty": 2,
      "enjoyment": 3,
      "path": "books/es/a2/Benin-a2-es.json",
      "word_count": 1835
    },
    {
      "id": "Canada-a2-es",
      "title": "Canada — Perfil del país (A2)",
      "language": "es",
      "level": "A2",
      "genre": [
        "Non-fiction"
      ],
      "difficulty": 2,
      "enjoyment": 3,
      "path": "books/es/a2/Canada-a2-es.json",
      "word_count": 1459
    },
    {
      "id": "Chile-a2-es",
      "title": "Chile — Perfil del país (A2)",
      "language": "es",
      "level": "A2",
      "genre": [
        "Non-fiction"
      ],
      "difficulty": 2,
      "enjoyment": 3,
      "path": "books/es/a2/Chile-a2-es.json",
      "word_count": 1514
    },
    {
      "id": "Czechia-a2-es",
      "title": "Czechia — Perfil del país (A2)",
      "language": "es",
      "level": "A2",
      "genre": [
        "Non-fiction"
      ],
      "difficulty": 2,
      "enjoyment": 3,
      "path": "books/es/a2/Czechia-a2-es.json",
      "word_count": 1494
    },
    {
      "id": "Denmark-a2-es",
      "title": "Denmark — Perfil del país (A2)",
      "language": "es",
      "level": "A2",
      "genre": [
        "Non-fiction"
      ],
      "difficulty": 2,
      "enjoyment": 3,
      "path": "books/es/a2/Denmark-a2-es.json",
      "word_count": 1462
    },
    {
      "id": "Egypt-a2-es",
      "title": "Egypt — Perfil del país (A2)",
      "language": "es",
      "level": "A2",
      "genre": [
        "Non-fiction"
      ],
      "difficulty": 2,
      "enjoyment": 3,
      "path": "books/es/a2/Egypt-a2-es.json",
      "word_count": 1407
    },
    {
      "id": "Ethiopia-a2-es",
      "title": "Ethiopia — Perfil del país (A2)",
      "language": "es",
      "level": "A2",
      "genre": [
        "Non-fiction"
      ],
      "difficulty": 2,
      "enjoyment": 3,
      "path": "books/es/a2/Ethiopia-a2-es.json",
      "word_count": 1580
    },
    {
      "id": "France-a2-es",
      "title": "France — Perfil del país (A2)",
      "language": "es",
      "level": "A2",
      "genre": [
        "Non-fiction"
      ],
      "difficulty": 2,
      "enjoyment": 3,
      "path": "books/es/a2/France-a2-es.json",
      "word_count": 1661
    },
    {
      "id": "Germany-a2-es",
      "title": "Germany — Perfil del país (A2)",
      "language": "es",
      "level": "A2",
      "genre": [
        "Non-fiction"
      ],
      "difficulty": 2,
      "enjoyment": 3,
      "path": "books/es/a2/Germany-a2-es.json",
      "word_count": 1530
    },
    {
      "id": "India-a2-es",
      "title": "India — Perfil del país (A2)",
      "language": "es",
      "level": "A2",
      "genre": [
        "Non-fiction"
      ],
      "difficulty": 2,
      "enjoyment": 3,
      "path": "books/es/a2/India-a2-es.json",
      "word_count": 1591
    },
    {
      "id": "Ireland-a2-es",
      "title": "Ireland — Perfil del país (A2)",
      "language": "es",
      "level": "A2",
      "genre": [
        "Non-fiction"
      ],
      "difficulty": 2,
      "enjoyment": 3,
      "path": "books/es/a2/Ireland-a2-es.json",
      "word_count": 1550
    },
    {
      "id": "Italy-a2-es",
      "title": "Italy — Perfil del país (A2)",
      "language": "es",
      "level": "A2",
      "genre": [
        "Non-fiction"
      ],
      "difficulty": 2,
      "enjoyment": 3,
      "path": "books/es/a2/Italy-a2-es.json",
      "word_count": 1770
    },
    {
      "id": "Japan-a2-es",
      "title": "Japan — Perfil del país (A2)",
      "language": "es",
      "level": "A2",
      "genre": [
        "Non-fiction"
      ],
      "difficulty": 2,
      "enjoyment": 3,
      "path": "books/es/a2/Japan-a2-es.json",
      "word_count": 1545
    },
    {
      "id": "Kenya-a2-es",
      "title": "Kenya — Perfil del país (A2)",
      "language": "es",
      "level": "A2",
      "genre": [
        "Non-fiction"
      ],
      "difficulty": 2,
      "enjoyment": 3,
      "path": "books/es/a2/Kenya-a2-es.json",
      "word_count": 1205
    },
    {
      "id": "Libya-a2-es",
      "title": "Libya — Perfil del país (A2)",
      "language": "es",
      "level": "A2",
      "genre": [
        "Non-fiction"
      ],
      "difficulty": 2,
      "enjoyment": 3,
      "path": "books/es/a2/Libya-a2-es.json",
      "word_count": 1602
    },
    {
      "id": "Mexico-a2-es",
      "title": "Mexico — Perfil del país (A2)",
      "language": "es",
      "level": "A2",
      "genre": [
        "Non-fiction"
      ],
      "difficulty": 2,
      "enjoyment": 3,
      "path": "books/es/a2/Mexico-a2-es.json",
      "word_count": 1659
    },
    {
      "id": "Mongolia-a2-es",
      "title": "Mongolia — Perfil del país (A2)",
      "language": "es",
      "level": "A2",
      "genre": [
        "Non-fiction"
      ],
      "difficulty": 2,
      "enjoyment": 3,
      "path": "books/es/a2/Mongolia-a2-es.json",
      "word_count": 1277
    },
    {
      "id": "Nepal-a2-es",
      "title": "Nepal — Perfil del país (A2)",
      "language": "es",
      "level": "A2",
      "genre": [
        "Non-fiction"
      ],
      "difficulty": 2,
      "enjoyment": 3,
      "path": "books/es/a2/Nepal-a2-es.json",
      "word_count": 1405
    },
    {
      "id": "New-Zealand-a2-es",
      "title": "New Zealand — Perfil del país (A2)",
      "language": "es",
      "level": "A2",
      "genre": [
        "Non-fiction"
      ],
      "difficulty": 2,
      "enjoyment": 3,
      "path": "books/es/a2/New-Zealand-a2-es.json",
      "word_count": 1480
    },
    {
      "id": "Pakistan-a2-es",
      "title": "Pakistan — Perfil del país (A2)",
      "language": "es",
      "level": "A2",
      "genre": [
        "Non-fiction"
      ],
      "difficulty": 2,
      "enjoyment": 3,
      "path": "books/es/a2/Pakistan-a2-es.json",
      "word_count": 1629
    },
    {
      "id": "Poland-a2-es",
      "title": "Poland — Perfil del país (A2)",
      "language": "es",
      "level": "A2",
      "genre": [
        "Non-fiction"
      ],
      "difficulty": 2,
      "enjoyment": 3,
      "path": "books/es/a2/Poland-a2-es.json",
      "word_count": 1601
    },
    {
      "id": "Russia-a2-es",
      "title": "Russia — Perfil del país (A2)",
      "language": "es",
      "level": "A2",
      "genre": [
        "Non-fiction"
      ],
      "difficulty": 2,
      "enjoyment": 3,
      "path": "books/es/a2/Russia-a2-es.json",
      "word_count": 1335
    },
    {
      "id": "South-Korea-a2-es",
      "title": "South Korea — Perfil del país (A2)",
      "language": "es",
      "level": "A2",
      "genre": [
        "Non-fiction"
      ],
      "difficulty": 2,
      "enjoyment": 3,
      "path": "books/es/a2/South-Korea-a2-es.json",
      "word_count": 1565
    },
    {
      "id": "Spain-a2-es",
      "title": "Spain — Perfil del país (A2)",
      "language": "es",
      "level": "A2",
      "genre": [
        "Non-fiction"
      ],
      "difficulty": 2,
      "enjoyment": 3,
      "path": "books/es/a2/Spain-a2-es.json",
      "word_count": 1581
    },
    {
      "id": "Thailand-a2-es",
      "title": "Thailand — Perfil del país (A2)",
      "language": "es",
      "level": "A2",
      "genre": [
        "Non-fiction"
      ],
      "difficulty": 2,
      "enjoyment": 3,
      "path": "books/es/a2/Thailand-a2-es.json",
      "word_count": 1229
    },
    {
      "id": "USA-a2-es",
      "title": "USA — Perfil del país (A2)",
      "language": "es",
      "level": "A2",
      "genre": [
        "Non-fiction"
      ],
      "difficulty": 2,
      "enjoyment": 3,
      "path": "books/es/a2/USA-a2-es.json",
      "word_count": 1680
    },
    {
      "id": "Ukraine-a2-es",
      "title": "Ukraine — Perfil del país (A2)",
      "language": "es",
      "level": "A2",
      "genre": [
        "Non-fiction"
      ],
      "difficulty": 2,
      "enjoyment": 3,
      "path": "books/es/a2/Ukraine-a2-es.json",
      "word_count": 1423
    },
    {
      "id": "Vietnam-a2-es",
      "title": "Vietnam — Perfil del país (A2)",
      "language": "es",
      "level": "A2",
      "genre": [
        "Non-fiction"
      ],
      "difficulty": 2,
      "enjoyment": 3,
      "path": "books/es/a2/Vietnam-a2-es.json",
      "word_count": 1317
    },
    {
      "id": "Zimbabwe-a2-es",
      "title": "Zimbabwe — Perfil del país (A2)",
      "language": "es",
      "level": "A2",
      "genre": [
        "Non-fiction"
      ],
      "difficulty": 2,
      "enjoyment": 3,
      "path": "books/es/a2/Zimbabwe-a2-es.json",
      "word_count": 1339
    },
    {
      "id": "biografia-de-alex-hurricane-higgins-a2-es",
      "title": "Biografía de Alex Hurricane Higgins",
      "language": "es",
      "level": "A2",
      "genre": [
        "biography"
      ],
      "difficulty": 3,
      "enjoyment": 3,
      "path": "books/es/a2/biografia-de-alex-hurricane-higgins-a2-es.json",
      "word_count": 2432
    },
    {
      "id": "biografia-de-erskine-childers-b1-chat-b1-es",
      "title": "Biografía de Erskine Childers B1 (Chat)",
      "language": "es",
      "level": "B1",
      "genre": [
        "biography"
      ],
      "difficulty": 3,
      "enjoyment": 3,
      "path": "books/es/b1/biografia-de-erskine-childers-b1-chat-b1-es.json",
      "word_count": 4359
    },
    {
      "id": "biografia-de-erskine-childers-b1-grok-b1-es",
      "title": "Biografía de Erskine Childers B1 Grok",
      "language": "es",
      "level": "B1",
      "genre": [
        "biography"
      ],
      "difficulty": 3,
      "enjoyment": 3,
      "path": "books/es/b1/biografia-de-erskine-childers-b1-grok-b1-es.json",
      "word_count": 3703
    },
    {
      "id": "biografia-de-j-m-barrie-b1-es",
      "title": "Biografía de J M Barrie",
      "language": "es",
      "level": "B1",
      "genre": [
        "biography"
      ],
      "difficulty": 3,
      "enjoyment": 3,
      "path": "books/es/b1/biografia-de-j-m-barrie-b1-es.json",
      "word_count": 3766
    },
    {
      "id": "biografia-de-marlene-dietrich-a2-es",
      "title": "Biografía de Marlene Dietrich",
      "language": "es",
      "level": "A2",
      "genre": [
        "biography"
      ],
      "difficulty": 3,
      "enjoyment": 3,
      "path": "books/es/a2/biografia-de-marlene-dietrich-a2-es.json",
      "word_count": 2390
    },
    {
      "id": "biografia-de-queen-elizabeth-ii-b2-es",
      "title": "Biografía de Queen Elizabeth II",
      "language": "es",
      "level": "B2",
      "genre": [
        "biography"
      ],
      "difficulty": 3,
      "enjoyment": 3,
      "path": "books/es/b2/biografia-de-queen-elizabeth-ii-b2-es.json",
      "word_count": 4854
    },
    {
      "id": "biografia-de-winston-churchill-a2-es",
      "title": "Biografía de Winston Churchill",
      "language": "es",
      "level": "A2",
      "genre": [
        "biography"
      ],
      "difficulty": 3,
      "enjoyment": 3,
      "path": "books/es/a2/biografia-de-winston-churchill-a2-es.json",
      "word_count": 2387
    },
    {
      "id": "dos-pueblos-un-corazon-a2-es",
      "title": "Dos pueblos, un corazón",
      "language": "es",
      "level": "A2",
      "genre": [
        "fiction"
      ],
      "difficulty": 3,
      "enjoyment": 3,
      "path": "books/es/a2/dos-pueblos-un-corazon-a2-es.json",
      "word_count": 3051
    },
    {
      "id": "el-camino-de-ana-a2-b1-es",
      "title": "El camino de Ana A2",
      "language": "es",
      "level": "B1",
      "genre": [
        "fiction"
      ],
      "difficulty": 3,
      "enjoyment": 3,
      "path": "books/es/b1/el-camino-de-ana-a2-b1-es.json",
      "word_count": 2193
    },
    {
      "id": "el-collar-a2-es",
      "title": "El collar",
      "language": "es",
      "level": "A2",
      "genre": [
        "short_story"
      ],
      "difficulty": 3,
      "enjoyment": 4,
      "word_count": 2642,
      "path": "books/es/a2/el-collar-a2-es.json"
    },
    {
      "id": "el-hotel-la-casa-del-roble-a2-v1-b1-es",
      "title": "El Hotel La Casa del Roble A2 V1",
      "language": "es",
      "level": "B1",
      "genre": [],
      "difficulty": 3,
      "enjoyment": 3,
      "path": "books/es/a2/el-hotel-la-casa-del-roble-a2-v1-b1-es.json",
      "word_count": 1157
    },
    {
      "id": "el-metodo-kanban-nivel-b1-b1-es",
      "title": "El método Kanban – Nivel B1",
      "language": "es",
      "level": "B1",
      "genre": [],
      "difficulty": 3,
      "enjoyment": 3,
      "word_count": 1860,
      "path": "books/es/b1/el-metodo-kanban-nivel-b1-b1-es.json"
    },
    {
      "id": "el-olor-de-los-recuerdos-a2-es",
      "title": "El olor de los recuerdos",
      "language": "es",
      "level": "A2",
      "genre": [
        "fiction"
      ],
      "difficulty": 3,
      "enjoyment": 3,
      "path": "books/es/a2/el-olor-de-los-recuerdos-a2-es.json",
      "word_count": 2849
    },
    {
      "id": "el-principio-80-20-analisis-de-pareto-nivel-b1-b1-es",
      "title": "El principio 80/20 (Análisis de Pareto) – Nivel B1",
      "language": "es",
      "level": "B1",
      "genre": [],
      "difficulty": 3,
      "enjoyment": 3,
      "word_count": 2078,
      "path": "books/es/b1/el-principio-80-20-analisis-de-pareto-nivel-b1-b1-es.json"
    },
    {
      "id": "george-iii-b1-es",
      "title": "George III",
      "language": "es",
      "level": "B1",
      "genre": [],
      "difficulty": 3,
      "enjoyment": 3,
      "path": "books/es/b1/george-iii-b1-es.json",
      "word_count": 1975
    },
    {
      "id": "gibraltar-b2-es",
      "title": "Gibraltar B2",
      "language": "es",
      "level": "B2",
      "genre": [],
      "difficulty": 3,
      "enjoyment": 3,
      "path": "books/es/b2/gibraltar-b2-es.json",
      "word_count": 4503
    },
    {
      "id": "giuseppe-verdi-b1-b1-es",
      "title": "Giuseppe Verdi B1",
      "language": "es",
      "level": "B1",
      "genre": [],
      "difficulty": 3,
      "enjoyment": 3,
      "path": "books/es/b1/giuseppe-verdi-b1-b1-es.json",
      "word_count": 3373
    },
    {
      "id": "henry-viii-b1-b1-es",
      "title": "Henry VIII B1",
      "language": "es",
      "level": "B1",
      "genre": [],
      "difficulty": 3,
      "enjoyment": 3,
      "path": "books/es/b1/henry-viii-b1-b1-es.json",
      "word_count": 3163
    },
    {
      "id": "isabel-i-de-castilla-b1-es",
      "title": "Isabel I de Castilla",
      "language": "es",
      "level": "B1",
      "genre": [
        "biography",
        "history"
      ],
      "difficulty": 3,
      "enjoyment": 4,
      "path": "books/es/b1/isabel-i-de-castilla-b1-es.json",
      "word_count": 4673
    },
    {
      "id": "la-geografia-del-litoral-b1-es",
      "title": "La geografía del litoral",
      "language": "es",
      "level": "B1",
      "genre": [
        "geography"
      ],
      "difficulty": 3,
      "enjoyment": 3,
      "path": "books/es/b1/la-geografia-del-litoral-b1-es.json",
      "word_count": 4892
    },
    {
      "id": "la-matriz-de-eisenhower-nivel-b1-b1-es",
      "title": "La Matriz de Eisenhower (Nivel B1)",
      "language": "es",
      "level": "B1",
      "genre": [],
      "difficulty": 3,
      "enjoyment": 3,
      "word_count": 2106,
      "path": "books/es/b1/la-matriz-de-eisenhower-nivel-b1-b1-es.json"
    },
    {
      "id": "la-primera-guerra-mundial-b1-es",
      "title": "La Primera Guerra Mundial",
      "language": "es",
      "level": "B1",
      "genre": [
        "history"
      ],
      "difficulty": 3,
      "enjoyment": 4,
      "path": "books/es/b1/la-primera-guerra-mundial-b1-es.json",
      "word_count": 5520
    },
    {
      "id": "la-tecnica-pomodoro-b1-b1-es",
      "title": "La Técnica Pomodoro B1",
      "language": "es",
      "level": "B1",
      "genre": [],
      "difficulty": 3,
      "enjoyment": 3,
      "word_count": 2255,
      "path": "books/es/b1/la-tecnica-pomodoro-b1-b1-es.json"
    },
    {
      "id": "la-tierra-v1-b1-b1-es",
      "title": "La Tierra V1 B1",
      "language": "es",
      "level": "B1",
      "genre": [],
      "difficulty": 3,
      "enjoyment": 3,
      "path": "books/es/b1/la-tierra-v1-b1-b1-es.json",
      "word_count": 2275
    },
    {
      "id": "la-tierra-v2-b1-b1-es",
      "title": "La Tierra V2 B1",
      "language": "es",
      "level": "B1",
      "genre": [],
      "difficulty": 3,
      "enjoyment": 3,
      "path": "books/es/b1/la-tierra-v2-b1-b1-es.json",
      "word_count": 2109
    },
    {
      "id": "la-tierra-v3-b1-b1-es",
      "title": "La Tierra V3 B1",
      "language": "es",
      "level": "B1",
      "genre": [],
      "difficulty": 3,
      "enjoyment": 3,
      "path": "books/es/b1/la-tierra-v3-b1-b1-es.json",
      "word_count": 2120
    },
    {
      "id": "la-tierra-v4-b1-b1-es",
      "title": "La Tierra V4 B1",
      "language": "es",
      "level": "B1",
      "genre": [],
      "difficulty": 3,
      "enjoyment": 3,
      "path": "books/es/b1/la-tierra-v4-b1-b1-es.json",
      "word_count": 1851
    },
    {
      "id": "las-senales-del-corazon-a2-es",
      "title": "Las señales del corazón",
      "language": "es",
      "level": "A2",
      "genre": [
        "fiction"
      ],
      "difficulty": 3,
      "enjoyment": 3,
      "path": "books/es/a2/las-senales-del-corazon-a2-es.json",
      "word_count": 2869
    },
    {
      "id": "mahatma-gandhi-b1-es",
      "title": "Mahatma Gandhi",
      "language": "es",
      "level": "B1",
      "genre": [],
      "difficulty": 3,
      "enjoyment": 3,
      "path": "books/es/b1/mahatma-gandhi-b1-es.json",
      "word_count": 2546
    },
    {
      "id": "mark-tully-b1-b1-es",
      "title": "Mark Tully B1",
      "language": "es",
      "level": "B1",
      "genre": [],
      "difficulty": 3,
      "enjoyment": 3,
      "path": "books/es/b1/mark-tully-b1-b1-es.json",
      "word_count": 3455
    },
    {
      "id": "organiza-tu-vida-con-el-metodo-getting-things-done-b1-b1-es",
      "title": "Organiza tu vida con el método Getting Things Done B1",
      "language": "es",
      "level": "B1",
      "genre": [],
      "difficulty": 3,
      "enjoyment": 3,
      "word_count": 2330,
      "path": "books/es/b1/organiza-tu-vida-con-el-metodo-getting-things-done-b1-b1-es.json"
    },
    {
      "id": "sección-1-una-mujer-que-quiere-más-a2-es",
      "title": "## **SECCIÓN 1 — Una mujer que quiere más**",
      "language": "es",
      "level": "A2",
      "genre": [
        "short_story"
      ],
      "difficulty": 3,
      "enjoyment": 4,
      "word_count": 2772,
      "path": "books/es/a2/sección-1-una-mujer-que-quiere-más-a2-es.json"
    },
    {
      "id": "time-blocking-b1-b1-es",
      "title": "Time Blocking B1",
      "language": "es",
      "level": "B1",
      "genre": [],
      "difficulty": 3,
      "enjoyment": 3,
      "word_count": 2241,
      "path": "books/es/b1/time-blocking-b1-b1-es.json"
    },
    {
      "id": "una-mujer-que-quiere-más-a2-es",
      "title": "# **Una mujer que quiere más**",
      "language": "es",
      "level": "A2",
      "genre": [
        "short_story"
      ],
      "difficulty": 3,
      "enjoyment": 4,
      "word_count": 2976,
      "path": "books/es/a2/una-mujer-que-quiere-más-a2-es.json"
    },
    {
      "id": "rugby-a1-es",
      "title": "Rugby — Lectura fácil (A1)",
      "language": "es",
      "level": "A1",
      "genre": [
        "Non-fiction"
      ],
      "difficulty": 1,
      "enjoyment": 3,
      "path": "books/es/a1/rugby-a1-es.json",
      "word_count": 150
    },
    {
      "id": "fútbol-a1-es",
      "title": "fútbol — Lectura fácil (A1)",
      "language": "es",
      "level": "A1",
      "genre": [
        "Non-fiction"
      ],
      "difficulty": 1,
      "enjoyment": 3,
      "path": "books/es/a1/fútbol-a1-es.json",
      "word_count": 148
    },
    {
      "id": "baloncesto-a1-es",
      "title": "baloncesto — Lectura fácil (A1)",
      "language": "es",
      "level": "A1",
      "genre": [
        "Non-fiction"
      ],
      "difficulty": 1,
      "enjoyment": 3,
      "path": "books/es/a1/baloncesto-a1-es.json",
      "word_count": 147
    },
    {
      "id": "críquet-a1-es",
      "title": "críquet — Lectura fácil (A1)",
      "language": "es",
      "level": "A1",
      "genre": [
        "Non-fiction"
      ],
      "difficulty": 1,
      "enjoyment": 3,
      "path": "books/es/a1/críquet-a1-es.json",
      "word_count": 144
    },
    {
      "id": "tenis-a1-es",
      "title": "tenis — Lectura fácil (A1)",
      "language": "es",
      "level": "A1",
      "genre": [
        "Non-fiction"
      ],
      "difficulty": 1,
      "enjoyment": 3,
      "path": "books/es/a1/tenis-a1-es.json",
      "word_count": 147
    },
    {
      "id": "hockey-sobre-césped-a1-es",
      "title": "hockey sobre césped — Lectura fácil (A1)",
      "language": "es",
      "level": "A1",
      "genre": [
        "Non-fiction"
      ],
      "difficulty": 1,
      "enjoyment": 3,
      "path": "books/es/a1/hockey-sobre-césped-a1-es.json",
      "word_count": 158
    },
    {
      "id": "voleibol-a1-es",
      "title": "voleibol — Lectura fácil (A1)",
      "language": "es",
      "level": "A1",
      "genre": [
        "Non-fiction"
      ],
      "difficulty": 1,
      "enjoyment": 3,
      "path": "books/es/a1/voleibol-a1-es.json",
      "word_count": 148
    },
    {
      "id": "tenis-de-mesa-a1-es",
      "title": "Tenis de mesa — Lectura fácil (A1)",
      "language": "es",
      "level": "A1",
      "genre": [
        "Non-fiction"
      ],
      "difficulty": 1,
      "enjoyment": 3,
      "path": "books/es/a1/tenis-de-mesa-a1-es.json",
      "word_count": 157
    },
    {
      "id": "béisbol-a1-es",
      "title": "béisbol — Lectura fácil (A1)",
      "language": "es",
      "level": "A1",
      "genre": [
        "Non-fiction"
      ],
      "difficulty": 1,
      "enjoyment": 3,
      "path": "books/es/a1/béisbol-a1-es.json",
      "word_count": 142
    },
    {
      "id": "fútbol-americano-a1-es",
      "title": "fútbol americano — Lectura fácil (A1)",
      "language": "es",
      "level": "A1",
      "genre": [
        "Non-fiction"
      ],
      "difficulty": 1,
      "enjoyment": 3,
      "path": "books/es/a1/fútbol-americano-a1-es.json",
      "word_count": 140
    },
    {
      "id": "rugby-league-a1-es",
      "title": "Rugby League — Lectura fácil (A1)",
      "language": "es",
      "level": "A1",
      "genre": [
        "Non-fiction"
      ],
      "difficulty": 1,
      "enjoyment": 3,
      "path": "books/es/a1/rugby-league-a1-es.json",
      "word_count": 141
    },
    {
      "id": "golf-a1-es",
      "title": "Golf — Lectura fácil (A1)",
      "language": "es",
      "level": "A1",
      "genre": [
        "Non-fiction"
      ],
      "difficulty": 1,
      "enjoyment": 3,
      "path": "books/es/a1/golf-a1-es.json",
      "word_count": 149
    },
    {
      "id": "boxeo-a1-es",
      "title": "boxeo — Lectura fácil (A1)",
      "language": "es",
      "level": "A1",
      "genre": [
        "Non-fiction"
      ],
      "difficulty": 1,
      "enjoyment": 3,
      "path": "books/es/a1/boxeo-a1-es.json",
      "word_count": 143
    },
    {
      "id": "hockey-sobre-hielo-a1-es",
      "title": "hockey sobre hielo — Lectura fácil (A1)",
      "language": "es",
      "level": "A1",
      "genre": [
        "Non-fiction"
      ],
      "difficulty": 1,
      "enjoyment": 3,
      "path": "books/es/a1/hockey-sobre-hielo-a1-es.json",
      "word_count": 141
    },
    {
      "id": "bádminton-a1-es",
      "title": "bádminton — Lectura fácil (A1)",
      "language": "es",
      "level": "A1",
      "genre": [
        "Non-fiction"
      ],
      "difficulty": 1,
      "enjoyment": 3,
      "path": "books/es/a1/bádminton-a1-es.json",
      "word_count": 143
    },
    {
      "id": "ciclismo-a1-es",
      "title": "ciclismo — Lectura fácil (A1)",
      "language": "es",
      "level": "A1",
      "genre": [
        "Non-fiction"
      ],
      "difficulty": 1,
      "enjoyment": 3,
      "path": "books/es/a1/ciclismo-a1-es.json",
      "word_count": 140
    },
    {
      "id": "natación-a1-es",
      "title": "natación — Lectura fácil (A1)",
      "language": "es",
      "level": "A1",
      "genre": [
        "Non-fiction"
      ],
      "difficulty": 1,
      "enjoyment": 3,
      "path": "books/es/a1/natación-a1-es.json",
      "word_count": 156
    },
    {
      "id": "atletismo-a1-es",
      "title": "atletismo — Lectura fácil (A1)",
      "language": "es",
      "level": "A1",
      "genre": [
        "Non-fiction"
      ],
      "difficulty": 1,
      "enjoyment": 3,
      "path": "books/es/a1/atletismo-a1-es.json",
      "word_count": 142
    },
    {
      "id": "lucha-libre-a1-es",
      "title": "lucha libre — Lectura fácil (A1)",
      "language": "es",
      "level": "A1",
      "genre": [
        "Non-fiction"
      ],
      "difficulty": 1,
      "enjoyment": 3,
      "path": "books/es/a1/lucha-libre-a1-es.json",
      "word_count": 146
    },
    {
      "id": "artes-marciales-mixtas-a1-es",
      "title": "Artes Marciales Mixtas — Lectura fácil (A1)",
      "language": "es",
      "level": "A1",
      "genre": [
        "Non-fiction"
      ],
      "difficulty": 1,
      "enjoyment": 3,
      "path": "books/es/a1/artes-marciales-mixtas-a1-es.json",
      "word_count": 142
    },
    {
      "id": "fórmula-1-a1-es",
      "title": "Fórmula 1 — Lectura fácil (A1)",
      "language": "es",
      "level": "A1",
      "genre": [
        "Non-fiction"
      ],
      "difficulty": 1,
      "enjoyment": 3,
      "path": "books/es/a1/fórmula-1-a1-es.json",
      "word_count": 149
    },
    {
      "id": "motociclismo-de-velocidad-a1-es",
      "title": "Motociclismo de velocidad — Lectura fácil (A1)",
      "language": "es",
      "level": "A1",
      "genre": [
        "Non-fiction"
      ],
      "difficulty": 1,
      "enjoyment": 3,
      "path": "books/es/a1/motociclismo-de-velocidad-a1-es.json",
      "word_count": 142
    },
    {
      "id": "surf-a1-es",
      "title": "surf — Lectura fácil (A1)",
      "language": "es",
      "level": "A1",
      "genre": [
        "Non-fiction"
      ],
      "difficulty": 1,
      "enjoyment": 3,
      "path": "books/es/a1/surf-a1-es.json",
      "word_count": 157
    },
    {
      "id": "esquí-alpino-a1-es",
      "title": "Esquí alpino — Lectura fácil (A1)",
      "language": "es",
      "level": "A1",
      "genre": [
        "Non-fiction"
      ],
      "difficulty": 1,
      "enjoyment": 3,
      "path": "books/es/a1/esquí-alpino-a1-es.json",
      "word_count": 143
    },
    {
      "id": "snowboard-a1-es",
      "title": "Snowboard — Lectura fácil (A1)",
      "language": "es",
      "level": "A1",
      "genre": [
        "Non-fiction"
      ],
      "difficulty": 1,
      "enjoyment": 3,
      "path": "books/es/a1/snowboard-a1-es.json",
      "word_count": 142
    },
    {
      "id": "gimnasia-a1-es",
      "title": "gimnasia — Lectura fácil (A1)",
      "language": "es",
      "level": "A1",
      "genre": [
        "Non-fiction"
      ],
      "difficulty": 1,
      "enjoyment": 3,
      "path": "books/es/a1/gimnasia-a1-es.json",
      "word_count": 141
    },
    {
      "id": "balonmano-a1-es",
      "title": "Balonmano — Lectura fácil (A1)",
      "language": "es",
      "level": "A1",
      "genre": [
        "Non-fiction"
      ],
      "difficulty": 1,
      "enjoyment": 3,
      "path": "books/es/a1/balonmano-a1-es.json",
      "word_count": 143
    },
    {
      "id": "polo-a1-es",
      "title": "polo — Lectura fácil (A1)",
      "language": "es",
      "level": "A1",
      "genre": [
        "Non-fiction"
      ],
      "difficulty": 1,
      "enjoyment": 3,
      "path": "books/es/a1/polo-a1-es.json",
      "word_count": 148
    },
    {
      "id": "polo-acuático-a1-es",
      "title": "polo acuático — Lectura fácil (A1)",
      "language": "es",
      "level": "A1",
      "genre": [
        "Non-fiction"
      ],
      "difficulty": 1,
      "enjoyment": 3,
      "path": "books/es/a1/polo-acuático-a1-es.json",
      "word_count": 148
    },
    {
      "id": "lacrosse-a1-es",
      "title": "lacrosse — Lectura fácil (A1)",
      "language": "es",
      "level": "A1",
      "genre": [
        "Non-fiction"
      ],
      "difficulty": 1,
      "enjoyment": 3,
      "path": "books/es/a1/lacrosse-a1-es.json",
      "word_count": 149
    },
    {
      "id": "sóftbol-a1-es",
      "title": "Sóftbol — Lectura fácil (A1)",
      "language": "es",
      "level": "A1",
      "genre": [
        "Non-fiction"
      ],
      "difficulty": 1,
      "enjoyment": 3,
      "path": "books/es/a1/sóftbol-a1-es.json",
      "word_count": 143
    },
    {
      "id": "ultimate-frisbee-a1-es",
      "title": "Ultimate Frisbee — Lectura fácil (A1)",
      "language": "es",
      "level": "A1",
      "genre": [
        "Non-fiction"
      ],
      "difficulty": 1,
      "enjoyment": 3,
      "path": "books/es/a1/ultimate-frisbee-a1-es.json",
      "word_count": 152
    },
    {
      "id": "patinaje-en-patineta-a1-es",
      "title": "Patinaje en patineta — Lectura fácil (A1)",
      "language": "es",
      "level": "A1",
      "genre": [
        "Non-fiction"
      ],
      "difficulty": 1,
      "enjoyment": 3,
      "path": "books/es/a1/patinaje-en-patineta-a1-es.json",
      "word_count": 145
    },
    {
      "id": "karate-a1-es",
      "title": "karate — Lectura fácil (A1)",
      "language": "es",
      "level": "A1",
      "genre": [
        "Non-fiction"
      ],
      "difficulty": 1,
      "enjoyment": 3,
      "path": "books/es/a1/karate-a1-es.json",
      "word_count": 142
    },
    {
      "id": "taekwondo-a1-es",
      "title": "Taekwondo — Lectura fácil (A1)",
      "language": "es",
      "level": "A1",
      "genre": [
        "Non-fiction"
      ],
      "difficulty": 1,
      "enjoyment": 3,
      "path": "books/es/a1/taekwondo-a1-es.json",
      "word_count": 150
    },
    {
      "id": "judo-a1-es",
      "title": "Judo — Lectura fácil (A1)",
      "language": "es",
      "level": "A1",
      "genre": [
        "Non-fiction"
      ],
      "difficulty": 1,
      "enjoyment": 3,
      "path": "books/es/a1/judo-a1-es.json",
      "word_count": 146
    },
    {
      "id": "bolos-sobre-césped-a1-es",
      "title": "Bolos sobre césped — Lectura fácil (A1)",
      "language": "es",
      "level": "A1",
      "genre": [
        "Non-fiction"
      ],
      "difficulty": 1,
      "enjoyment": 3,
      "path": "books/es/a1/bolos-sobre-césped-a1-es.json",
      "word_count": 144
    },
    {
      "id": "dardos-a1-es",
      "title": "dardos — Lectura fácil (A1)",
      "language": "es",
      "level": "A1",
      "genre": [
        "Non-fiction"
      ],
      "difficulty": 1,
      "enjoyment": 3,
      "path": "books/es/a1/dardos-a1-es.json",
      "word_count": 141
    },
    {
      "id": "carreras-de-caballos-a1-es",
      "title": "Carreras de caballos — Lectura fácil (A1)",
      "language": "es",
      "level": "A1",
      "genre": [
        "Non-fiction"
      ],
      "difficulty": 1,
      "enjoyment": 3,
      "path": "books/es/a1/carreras-de-caballos-a1-es.json",
      "word_count": 147
    },
    {
      "id": "sepak-takraw-a1-es",
      "title": "Sepak Takraw — Lectura fácil (A1)",
      "language": "es",
      "level": "A1",
      "genre": [
        "Non-fiction"
      ],
      "difficulty": 1,
      "enjoyment": 3,
      "path": "books/es/a1/sepak-takraw-a1-es.json",
      "word_count": 140
    },
    {
      "id": "deportes-electrónicos-a1-es",
      "title": "deportes electrónicos — Lectura fácil (A1)",
      "language": "es",
      "level": "A1",
      "genre": [
        "Non-fiction"
      ],
      "difficulty": 1,
      "enjoyment": 3,
      "path": "books/es/a1/deportes-electrónicos-a1-es.json",
      "word_count": 151
    },
    {
      "id": "triatlón-a1-es",
      "title": "Triatlón — Lectura fácil (A1)",
      "language": "es",
      "level": "A1",
      "genre": [
        "Non-fiction"
      ],
      "difficulty": 1,
      "enjoyment": 3,
      "path": "books/es/a1/triatlón-a1-es.json",
      "word_count": 140
    },
    {
      "id": "levantamiento-de-pesas-a1-es",
      "title": "levantamiento de pesas — Lectura fácil (A1)",
      "language": "es",
      "level": "A1",
      "genre": [
        "Non-fiction"
      ],
      "difficulty": 1,
      "enjoyment": 3,
      "path": "books/es/a1/levantamiento-de-pesas-a1-es.json",
      "word_count": 157
    },
    {
      "id": "vela-a1-es",
      "title": "vela — Lectura fácil (A1)",
      "language": "es",
      "level": "A1",
      "genre": [
        "Non-fiction"
      ],
      "difficulty": 1,
      "enjoyment": 3,
      "path": "books/es/a1/vela-a1-es.json",
      "word_count": 142
    },
    {
      "id": "tiro-con-arco-a1-es",
      "title": "Tiro con arco — Lectura fácil (A1)",
      "language": "es",
      "level": "A1",
      "genre": [
        "Non-fiction"
      ],
      "difficulty": 1,
      "enjoyment": 3,
      "path": "books/es/a1/tiro-con-arco-a1-es.json",
      "word_count": 144
    },
    {
      "id": "esgrima-a1-es",
      "title": "Esgrima — Lectura fácil (A1)",
      "language": "es",
      "level": "A1",
      "genre": [
        "Non-fiction"
      ],
      "difficulty": 1,
      "enjoyment": 3,
      "path": "books/es/a1/esgrima-a1-es.json",
      "word_count": 145
    },
    {
      "id": "snooker-a1-es",
      "title": "snooker — Lectura fácil (A1)",
      "language": "es",
      "level": "A1",
      "genre": [
        "Non-fiction"
      ],
      "difficulty": 1,
      "enjoyment": 3,
      "path": "books/es/a1/snooker-a1-es.json",
      "word_count": 152
    },
    {
      "id": "billar-a1-es",
      "title": "Billar — Lectura fácil (A1)",
      "language": "es",
      "level": "A1",
      "genre": [
        "Non-fiction"
      ],
      "difficulty": 1,
      "enjoyment": 3,
      "path": "books/es/a1/billar-a1-es.json",
      "word_count": 143
    },
    {
      "id": "animación-deportiva-a1-es",
      "title": "animación deportiva — Lectura fácil (A1)",
      "language": "es",
      "level": "A1",
      "genre": [
        "Non-fiction"
      ],
      "difficulty": 1,
      "enjoyment": 3,
      "path": "books/es/a1/animación-deportiva-a1-es.json",
      "word_count": 140
    },
    {
      "id": "orientación-a1-es",
      "title": "Orientación — Lectura fácil (A1)",
      "language": "es",
      "level": "A1",
      "genre": [
        "Non-fiction"
      ],
      "difficulty": 1,
      "enjoyment": 3,
      "path": "books/es/a1/orientación-a1-es.json",
      "word_count": 141
    },
    {
      "id": "boccia-a1-es",
      "title": "boccia — Lectura fácil (A1)",
      "language": "es",
      "level": "A1",
      "genre": [
        "Non-fiction"
      ],
      "difficulty": 1,
      "enjoyment": 3,
      "path": "books/es/a1/boccia-a1-es.json",
      "word_count": 158
    },
    {
      "id": "petanca-a1-es",
      "title": "Petanca — Lectura fácil (A1)",
      "language": "es",
      "level": "A1",
      "genre": [
        "Non-fiction"
      ],
      "difficulty": 1,
      "enjoyment": 3,
      "path": "books/es/a1/petanca-a1-es.json",
      "word_count": 145
    }
  ]
}
