{
  "id": "animación-deportiva-a1-es",
  "title": "animación deportiva — Lectura fácil (A1)",
  "language": "es",
  "level": "A1",
  "genre": [
    "Non-fiction"
  ],
  "author": "",
  "blurb": "",
  "difficulty": 1,
  "enjoyment": 3,
  "chapters": [
    {
      "title": "Sección 1 — animación deportiva",
      "text": "La animación deportiva es un deporte muy divertido. Las personas que hacen animación deportiva se llaman animadores o animadoras. Ellos y ellas llevan ropa especial para moverse bien. La animación deportiva se practica en lugares grandes, como gimnasios o estadios. Los animadores hacen muchos movimientos con el cuerpo. Saltan, bailan y usan las manos y los brazos para hacer figuras. También forman pirámides con otras personas. La animación deportiva es un deporte de equipo. Todos trabajan juntos para crear un buen espectáculo. La gente que ve la animación deportiva se siente feliz y animada. Les gusta porque es alegre y entretenida. La animación deportiva ayuda a tener fuerza, equilibrio y buena salud. Muchas personas practican animación deportiva en la escuela o en clubes. Es un deporte para todas las edades. La animación deportiva une a las personas y crea amistad."
    }
  ],
  "word_count": 140
}
